CHANGELOG.md
LICENSE
MANIFEST.in
README.md
setup.py
nameshark_vcard/__init__.py
nameshark_vcard/nameshark_vcard.py
nameshark_vcard.egg-info/PKG-INFO
nameshark_vcard.egg-info/SOURCES.txt
nameshark_vcard.egg-info/dependency_links.txt
nameshark_vcard.egg-info/requires.txt
nameshark_vcard.egg-info/top_level.txt