Metadata-Version: 1.1
Name: nameshark-vcard
Version: 1.0.0
Summary: Converts vcards to the json format expected by the Name Shark app
Home-page: https://github.com/proinsias/nameshark-vcard
Author: Francis O'Donovan
Author-email: francis.odonovan@gmail.com
License: MIT
Platform: UNKNOWN
Classifier: Development Status :: 4 - Beta
Classifier: Intended Audience :: Developers
Classifier: Topic :: Software Development
Classifier: License :: OSI Approved :: MIT License
Classifier: Programming Language :: Python :: 2
Classifier: Programming Language :: Python :: 2.7
Classifier: Programming Language :: Python :: 3
Classifier: Programming Language :: Python :: 3.4
Classifier: Programming Language :: Python :: 3.5
Classifier: Programming Language :: Python :: 3.6
